{
  "resourceType": "Bundle",
  "type": "transaction",
  "entry": [
    {
      "fullUrl": "urn:uuid:8b58cdd1-3d79-3126-8fe0-da2c54d6805c",
      "resource": {
        "resourceType": "Organization",
        "id": "8b58cdd1-3d79-3126-8fe0-da2c54d6805c",
        "extension": [
          {
            "url": "http://synthetichealth.github.io/synthea/utilization-encounters-extension",
            "valueInteger": 8
          },
          {
            "url": "http://synthetichealth.github.io/synthea/utilization-procedures-extension",
            "valueInteger": 0
          },
          {
            "url": "http://synthetichealth.github.io/synthea/utilization-labs-extension",
            "valueInteger": 0
          },
          {
            "url": "http://synthetichealth.github.io/synthea/utilization-prescriptions-extension",
            "valueInteger": 0
          }
        ],
        "identifier": [
          {
            "system": "https://github.com/synthetichealth/synthea",
            "value": "8b58cdd1-3d79-3126-8fe0-da2c54d6805c"
          }
        ],
        "active": true,
        "type": [
          {
            "coding": [
              {
                "system": "http://terminology.hl7.org/CodeSystem/organization-type",
                "code": "prov",
                "display": "Healthcare Provider"
              }
            ],
            "text": "Healthcare Provider"
          }
        ],
        "name": "CARNEY HOSPITAL",
        "telecom": [
          {
            "system": "phone",
            "value": "6175062000"
          }
        ],
        "address": [
          {
            "line": [
              "2100 DORCHESTER AVENUE"
            ],
            "city": "BOSTON",
            "state": "MA",
            "postalCode": "02124",
            "country": "US"
          }
        ]
      },
      "request": {
        "method": "POST",
        "url": "Organization"
      }
    },
    {
      "fullUrl": "urn:uuid:5844ad77-f653-3c2b-b7dd-e97576ab3b03",
      "resource": {
        "resourceType": "Organization",
        "id": "5844ad77-f653-3c2b-b7dd-e97576ab3b03",
        "extension": [
          {
            "url": "http://synthetichealth.github.io/synthea/utilization-encounters-extension",
            "valueInteger": 29
          },
          {
            "url": "http://synthetichealth.github.io/synthea/utilization-procedures-extension",
            "valueInteger": 0
          },
          {
            "url": "http://synthetichealth.github.io/synthea/utilization-labs-extension",
            "valueInteger": 0
          },
          {
            "url": "http://synthetichealth.github.io/synthea/utilization-prescriptions-extension",
            "valueInteger": 0
          }
        ],
        "identifier": [
          {
            "system": "https://github.com/synthetichealth/synthea",
            "value": "5844ad77-f653-3c2b-b7dd-e97576ab3b03"
          }
        ],
        "active": true,
        "type": [
          {
            "coding": [
              {
                "system": "http://terminology.hl7.org/CodeSystem/organization-type",
                "code": "prov",
                "display": "Healthcare Provider"
              }
            ],
            "text": "Healthcare Provider"
          }
        ],
        "name": "BAYSTATE WING HOSPITAL AND MEDICAL CENTERS",
        "telecom": [
          {
            "system": "phone",
            "value": "4132837651"
          }
        ],
        "address": [
          {
            "line": [
              "40 WRIGHT STREET"
            ],
            "city": "PALMER",
            "state": "MA",
            "postalCode": "01069",
            "country": "US"
          }
        ]
      },
      "request": {
        "method": "POST",
        "url": "Organization"
      }
    },
    {
      "fullUrl": "urn:uuid:08bcda9c-f8c8-3244-82d4-fc306a7a55d3",
      "resource": {
        "resourceType": "Organization",
        "id": "08bcda9c-f8c8-3244-82d4-fc306a7a55d3",
        "extension": [
          {
            "url": "http://synthetichealth.github.io/synthea/utilization-encounters-extension",
            "valueInteger": 1
          },
          {
            "url": "http://synthetichealth.github.io/synthea/utilization-procedures-extension",
            "valueInteger": 0
          },
          {
            "url": "http://synthetichealth.github.io/synthea/utilization-labs-extension",
            "valueInteger": 0
          },
          {
            "url": "http://synthetichealth.github.io/synthea/utilization-prescriptions-extension",
            "valueInteger": 0
          }
        ],
        "identifier": [
          {
            "system": "https://github.com/synthetichealth/synthea",
            "value": "08bcda9c-f8c8-3244-82d4-fc306a7a55d3"
          }
        ],
        "active": true,
        "type": [
          {
            "coding": [
              {
                "system": "http://terminology.hl7.org/CodeSystem/organization-type",
                "code": "prov",
                "display": "Healthcare Provider"
              }
            ],
            "text": "Healthcare Provider"
          }
        ],
        "name": "BOSTON MEDICAL CENTER CORPORATION-",
        "telecom": [
          {
            "system": "phone",
            "value": "6176388000"
          }
        ],
        "address": [
          {
            "line": [
              "1 BOSTON MEDICAL CENTER PLACE"
            ],
            "city": "BOSTON",
            "state": "MA",
            "postalCode": "02118",
            "country": "US"
          }
        ]
      },
      "request": {
        "method": "POST",
        "url": "Organization"
      }
    },
    {
      "fullUrl": "urn:uuid:d78e84ec-30aa-3bba-a33a-f29a3a454662",
      "resource": {
        "resourceType": "Organization",
        "id": "d78e84ec-30aa-3bba-a33a-f29a3a454662",
        "extension": [
          {
            "url": "http://synthetichealth.github.io/synthea/utilization-encounters-extension",
            "valueInteger": 12
          },
          {
            "url": "http://synthetichealth.github.io/synthea/utilization-procedures-extension",
            "valueInteger": 0
          },
          {
            "url": "http://synthetichealth.github.io/synthea/utilization-labs-extension",
            "valueInteger": 0
          },
          {
            "url": "http://synthetichealth.github.io/synthea/utilization-prescriptions-extension",
            "valueInteger": 0
          }
        ],
        "identifier": [
          {
            "system": "https://github.com/synthetichealth/synthea",
            "value": "d78e84ec-30aa-3bba-a33a-f29a3a454662"
          }
        ],
        "active": true,
        "type": [
          {
            "coding": [
              {
                "system": "http://terminology.hl7.org/CodeSystem/organization-type",
                "code": "prov",
                "display": "Healthcare Provider"
              }
            ],
            "text": "Healthcare Provider"
          }
        ],
        "name": "MASSACHUSETTS GENERAL HOSPITAL",
        "telecom": [
          {
            "system": "phone",
            "value": "6177262000"
          }
        ],
        "address": [
          {
            "line": [
              "55 FRUIT STREET"
            ],
            "city": "BOSTON",
            "state": "MA",
            "postalCode": "02114",
            "country": "US"
          }
        ]
      },
      "request": {
        "method": "POST",
        "url": "Organization"
      }
    },
    {
      "fullUrl": "urn:uuid:7fb56531-86bd-3e4a-8619-4df9942da309",
      "resource": {
        "resourceType": "Organization",
        "id": "7fb56531-86bd-3e4a-8619-4df9942da309",
        "extension": [
          {
            "url": "http://synthetichealth.github.io/synthea/utilization-encounters-extension",
            "valueInteger": 4
          },
          {
            "url": "http://synthetichealth.github.io/synthea/utilization-procedures-extension",
            "valueInteger": 0
          },
          {
            "url": "http://synthetichealth.github.io/synthea/utilization-labs-extension",
            "valueInteger": 0
          },
          {
            "url": "http://synthetichealth.github.io/synthea/utilization-prescriptions-extension",
            "valueInteger": 0
          }
        ],
        "identifier": [
          {
            "system": "https://github.com/synthetichealth/synthea",
            "value": "7fb56531-86bd-3e4a-8619-4df9942da309"
          }
        ],
        "active": true,
        "type": [
          {
            "coding": [
              {
                "system": "http://terminology.hl7.org/CodeSystem/organization-type",
                "code": "prov",
                "display": "Healthcare Provider"
              }
            ],
            "text": "Healthcare Provider"
          }
        ],
        "name": "BETH ISRAEL DEACONESS HOSPITAL - NEEDHAM",
        "telecom": [
          {
            "system": "phone",
            "value": "7814533002"
          }
        ],
        "address": [
          {
            "line": [
              "148 CHESTNUT STREET"
            ],
            "city": "NEEDHAM",
            "state": "MA",
            "postalCode": "02494",
            "country": "US"
          }
        ]
      },
      "request": {
        "method": "POST",
        "url": "Organization"
      }
    },
    {
      "fullUrl": "urn:uuid:24cb4eab-6166-3530-bddc-a5a8a14a4fc1",
      "resource": {
        "resourceType": "Organization",
        "id": "24cb4eab-6166-3530-bddc-a5a8a14a4fc1",
        "extension": [
          {
            "url": "http://synthetichealth.github.io/synthea/utilization-encounters-extension",
            "valueInteger": 103
          },
          {
            "url": "http://synthetichealth.github.io/synthea/utilization-procedures-extension",
            "valueInteger": 0
          },
          {
            "url": "http://synthetichealth.github.io/synthea/utilization-labs-extension",
            "valueInteger": 0
          },
          {
            "url": "http://synthetichealth.github.io/synthea/utilization-prescriptions-extension",
            "valueInteger": 0
          }
        ],
        "identifier": [
          {
            "system": "https://github.com/synthetichealth/synthea",
            "value": "24cb4eab-6166-3530-bddc-a5a8a14a4fc1"
          }
        ],
        "active": true,
        "type": [
          {
            "coding": [
              {
                "system": "http://terminology.hl7.org/CodeSystem/organization-type",
                "code": "prov",
                "display": "Healthcare Provider"
              }
            ],
            "text": "Healthcare Provider"
          }
        ],
        "name": "MILFORD REGIONAL MEDICAL CENTER",
        "telecom": [
          {
            "system": "phone",
            "value": "5084731190"
          }
        ],
        "address": [
          {
            "line": [
              "14 PROSPECT STREET"
            ],
            "city": "MILFORD",
            "state": "MA",
            "postalCode": "01757",
            "country": "US"
          }
        ]
      },
      "request": {
        "method": "POST",
        "url": "Organization"
      }
    },
    {
      "fullUrl": "urn:uuid:465de31f-3098-365c-af70-48a071e1f5aa",
      "resource": {
        "resourceType": "Organization",
        "id": "465de31f-3098-365c-af70-48a071e1f5aa",
        "extension": [
          {
            "url": "http://synthetichealth.github.io/synthea/utilization-encounters-extension",
            "valueInteger": 70
          },
          {
            "url": "http://synthetichealth.github.io/synthea/utilization-procedures-extension",
            "valueInteger": 0
          },
          {
            "url": "http://synthetichealth.github.io/synthea/utilization-labs-extension",
            "valueInteger": 0
          },
          {
            "url": "http://synthetichealth.github.io/synthea/utilization-prescriptions-extension",
            "valueInteger": 0
          }
        ],
        "identifier": [
          {
            "system": "https://github.com/synthetichealth/synthea",
            "value": "465de31f-3098-365c-af70-48a071e1f5aa"
          }
        ],
        "active": true,
        "type": [
          {
            "coding": [
              {
                "system": "http://terminology.hl7.org/CodeSystem/organization-type",
                "code": "prov",
                "display": "Healthcare Provider"
              }
            ],
            "text": "Healthcare Provider"
          }
        ],
        "name": "METROWEST MEDICAL CENTER",
        "telecom": [
          {
            "system": "phone",
            "value": "5083831000"
          }
        ],
        "address": [
          {
            "line": [
              "115 LINCOLN STREET"
            ],
            "city": "FRAMINGHAM",
            "state": "MA",
            "postalCode": "01701",
            "country": "US"
          }
        ]
      },
      "request": {
        "method": "POST",
        "url": "Organization"
      }
    },
    {
      "fullUrl": "urn:uuid:d7b11827-25f2-350b-bcd8-939fc59851b0",
      "resource": {
        "resourceType": "Organization",
        "id": "d7b11827-25f2-350b-bcd8-939fc59851b0",
        "extension": [
          {
            "url": "http://synthetichealth.github.io/synthea/utilization-encounters-extension",
            "valueInteger": 74
          },
          {
            "url": "http://synthetichealth.github.io/synthea/utilization-procedures-extension",
            "valueInteger": 0
          },
          {
            "url": "http://synthetichealth.github.io/synthea/utilization-labs-extension",
            "valueInteger": 0
          },
          {
            "url": "http://synthetichealth.github.io/synthea/utilization-prescriptions-extension",
            "valueInteger": 0
          }
        ],
        "identifier": [
          {
            "system": "https://github.com/synthetichealth/synthea",
            "value": "d7b11827-25f2-350b-bcd8-939fc59851b0"
          }
        ],
        "active": true,
        "type": [
          {
            "coding": [
              {
                "system": "http://terminology.hl7.org/CodeSystem/organization-type",
                "code": "prov",
                "display": "Healthcare Provider"
              }
            ],
            "text": "Healthcare Provider"
          }
        ],
        "name": "BOSTON CHILDREN'S HOSPITAL",
        "telecom": [
          {
            "system": "phone",
            "value": "6177356000"
          }
        ],
        "address": [
          {
            "line": [
              "300 LONGWOOD AVENUE"
            ],
            "city": "BOSTON",
            "state": "MA",
            "postalCode": "02115",
            "country": "US"
          }
        ]
      },
      "request": {
        "method": "POST",
        "url": "Organization"
      }
    },
    {
      "fullUrl": "urn:uuid:869ba21d-a974-3260-9752-4d1ba8d12f28",
      "resource": {
        "resourceType": "Organization",
        "id": "869ba21d-a974-3260-9752-4d1ba8d12f28",
        "extension": [
          {
            "url": "http://synthetichealth.github.io/synthea/utilization-encounters-extension",
            "valueInteger": 9
          },
          {
            "url": "http://synthetichealth.github.io/synthea/utilization-procedures-extension",
            "valueInteger": 5
          },
          {
            "url": "http://synthetichealth.github.io/synthea/utilization-labs-extension",
            "valueInteger": 1
          },
          {
            "url": "http://synthetichealth.github.io/synthea/utilization-prescriptions-extension",
            "valueInteger": 3
          }
        ],
        "identifier": [
          {
            "system": "https://github.com/synthetichealth/synthea",
            "value": "869ba21d-a974-3260-9752-4d1ba8d12f28"
          }
        ],
        "active": true,
        "type": [
          {
            "coding": [
              {
                "system": "http://terminology.hl7.org/CodeSystem/organization-type",
                "code": "prov",
                "display": "Healthcare Provider"
              }
            ],
            "text": "Healthcare Provider"
          }
        ],
        "name": "PCP2617",
        "telecom": [
          {
            "system": "phone",
            "value": "781-894-8898"
          }
        ],
        "address": [
          {
            "line": [
              "102 WESTLAND RD"
            ],
            "city": "WESTON",
            "state": "MA",
            "postalCode": "02493-1341",
            "country": "US"
          }
        ]
      },
      "request": {
        "method": "POST",
        "url": "Organization"
      }
    },
    {
      "fullUrl": "urn:uuid:29564e82-e7f8-3aeb-8d9c-1e3fd73ca340",
      "resource": {
        "resourceType": "Organization",
        "id": "29564e82-e7f8-3aeb-8d9c-1e3fd73ca340",
        "extension": [
          {
            "url": "http://synthetichealth.github.io/synthea/utilization-encounters-extension",
            "valueInteger": 36
          },
          {
            "url": "http://synthetichealth.github.io/synthea/utilization-procedures-extension",
            "valueInteger": 183
          },
          {
            "url": "http://synthetichealth.github.io/synthea/utilization-labs-extension",
            "valueInteger": 13
          },
          {
            "url": "http://synthetichealth.github.io/synthea/utilization-prescriptions-extension",
            "valueInteger": 17
          }
        ],
        "identifier": [
          {
            "system": "https://github.com/synthetichealth/synthea",
            "value": "29564e82-e7f8-3aeb-8d9c-1e3fd73ca340"
          }
        ],
        "active": true,
        "type": [
          {
            "coding": [
              {
                "system": "http://terminology.hl7.org/CodeSystem/organization-type",
                "code": "prov",
                "display": "Healthcare Provider"
              }
            ],
            "text": "Healthcare Provider"
          }
        ],
        "name": "PCP16674",
        "telecom": [
          {
            "system": "phone",
            "value": "508-881-4443"
          }
        ],
        "address": [
          {
            "line": [
              "1 W UNION ST"
            ],
            "city": "ASHLAND",
            "state": "MA",
            "postalCode": "01721-1463",
            "country": "US"
          }
        ]
      },
      "request": {
        "method": "POST",
        "url": "Organization"
      }
    },
    {
      "fullUrl": "urn:uuid:04b0900a-2ae4-3360-b9a5-1b3eb2bdd8a2",
      "resource": {
        "resourceType": "Organization",
        "id": "04b0900a-2ae4-3360-b9a5-1b3eb2bdd8a2",
        "extension": [
          {
            "url": "http://synthetichealth.github.io/synthea/utilization-encounters-extension",
            "valueInteger": 62
          },
          {
            "url": "http://synthetichealth.github.io/synthea/utilization-procedures-extension",
            "valueInteger": 32
          },
          {
            "url": "http://synthetichealth.github.io/synthea/utilization-labs-extension",
            "valueInteger": 19
          },
          {
            "url": "http://synthetichealth.github.io/synthea/utilization-prescriptions-extension",
            "valueInteger": 55
          }
        ],
        "identifier": [
          {
            "system": "https://github.com/synthetichealth/synthea",
            "value": "04b0900a-2ae4-3360-b9a5-1b3eb2bdd8a2"
          }
        ],
        "active": true,
        "type": [
          {
            "coding": [
              {
                "system": "http://terminology.hl7.org/CodeSystem/organization-type",
                "code": "prov",
                "display": "Healthcare Provider"
              }
            ],
            "text": "Healthcare Provider"
          }
        ],
        "name": "PCP67456",
        "telecom": [
          {
            "system": "phone",
            "value": "202-445-7271"
          }
        ],
        "address": [
          {
            "line": [
              "140 N VALLEY RD"
            ],
            "city": "PELHAM",
            "state": "MA",
            "postalCode": "01002-9766",
            "country": "US"
          }
        ]
      },
      "request": {
        "method": "POST",
        "url": "Organization"
      }
    },
    {
      "fullUrl": "urn:uuid:b0d46e53-6b47-354a-9ddb-9ed9302ae9f5",
      "resource": {
        "resourceType": "Organization",
        "id": "b0d46e53-6b47-354a-9ddb-9ed9302ae9f5",
        "extension": [
          {
            "url": "http://synthetichealth.github.io/synthea/utilization-encounters-extension",
            "valueInteger": 59
          },
          {
            "url": "http://synthetichealth.github.io/synthea/utilization-procedures-extension",
            "valueInteger": 200
          },
          {
            "url": "http://synthetichealth.github.io/synthea/utilization-labs-extension",
            "valueInteger": 51
          },
          {
            "url": "http://synthetichealth.github.io/synthea/utilization-prescriptions-extension",
            "valueInteger": 24
          }
        ],
        "identifier": [
          {
            "system": "https://github.com/synthetichealth/synthea",
            "value": "b0d46e53-6b47-354a-9ddb-9ed9302ae9f5"
          }
        ],
        "active": true,
        "type": [
          {
            "coding": [
              {
                "system": "http://terminology.hl7.org/CodeSystem/organization-type",
                "code": "prov",
                "display": "Healthcare Provider"
              }
            ],
            "text": "Healthcare Provider"
          }
        ],
        "name": "PCP114062",
        "address": [
          {
            "line": [
              "77 W MAIN ST"
            ],
            "city": "HOPKINTON",
            "state": "MA",
            "postalCode": "01748-1684",
            "country": "US"
          }
        ]
      },
      "request": {
        "method": "POST",
        "url": "Organization"
      }
    },
    {
      "fullUrl": "urn:uuid:b8e926d3-93fe-3118-ae14-604751bfa993",
      "resource": {
        "resourceType": "Organization",
        "id": "b8e926d3-93fe-3118-ae14-604751bfa993",
        "extension": [
          {
            "url": "http://synthetichealth.github.io/synthea/utilization-encounters-extension",
            "valueInteger": 53
          },
          {
            "url": "http://synthetichealth.github.io/synthea/utilization-procedures-extension",
            "valueInteger": 297
          },
          {
            "url": "http://synthetichealth.github.io/synthea/utilization-labs-extension",
            "valueInteger": 36
          },
          {
            "url": "http://synthetichealth.github.io/synthea/utilization-prescriptions-extension",
            "valueInteger": 43
          }
        ],
        "identifier": [
          {
            "system": "https://github.com/synthetichealth/synthea",
            "value": "b8e926d3-93fe-3118-ae14-604751bfa993"
          }
        ],
        "active": true,
        "type": [
          {
            "coding": [
              {
                "system": "http://terminology.hl7.org/CodeSystem/organization-type",
                "code": "prov",
                "display": "Healthcare Provider"
              }
            ],
            "text": "Healthcare Provider"
          }
        ],
        "name": "MEDICAL CARE OF BOSTON MANAGEMENT CORPORATION",
        "telecom": [
          {
            "system": "phone",
            "value": "617-660-6700"
          }
        ],
        "address": [
          {
            "line": [
              "1000 BROADWAY"
            ],
            "city": "CHELSEA",
            "state": "MA",
            "postalCode": "02150-2247",
            "country": "US"
          }
        ]
      },
      "request": {
        "method": "POST",
        "url": "Organization"
      }
    },
    {
      "fullUrl": "urn:uuid:d672f853-e2a5-324e-98fa-c6d5f8dfc255",
      "resource": {
        "resourceType": "Organization",
        "id": "d672f853-e2a5-324e-98fa-c6d5f8dfc255",
        "extension": [
          {
            "url": "http://synthetichealth.github.io/synthea/utilization-encounters-extension",
            "valueInteger": 1
          },
          {
            "url": "http://synthetichealth.github.io/synthea/utilization-procedures-extension",
            "valueInteger": 0
          },
          {
            "url": "http://synthetichealth.github.io/synthea/utilization-labs-extension",
            "valueInteger": 0
          },
          {
            "url": "http://synthetichealth.github.io/synthea/utilization-prescriptions-extension",
            "valueInteger": 0
          }
        ],
        "identifier": [
          {
            "system": "https://github.com/synthetichealth/synthea",
            "value": "d672f853-e2a5-324e-98fa-c6d5f8dfc255"
          }
        ],
        "active": true,
        "type": [
          {
            "coding": [
              {
                "system": "http://terminology.hl7.org/CodeSystem/organization-type",
                "code": "prov",
                "display": "Healthcare Provider"
              }
            ],
            "text": "Healthcare Provider"
          }
        ],
        "name": "WALTHAM URGENT CARE",
        "telecom": [
          {
            "system": "phone",
            "value": "617-243-5591"
          }
        ],
        "address": [
          {
            "line": [
              "9 HOPE AVENUE"
            ],
            "city": "WALTHAM",
            "state": "MA",
            "postalCode": "2453",
            "country": "US"
          }
        ]
      },
      "request": {
        "method": "POST",
        "url": "Organization"
      }
    },
    {
      "fullUrl": "urn:uuid:7ffe74ac-786d-3c6d-bcb9-323352f6149c",
      "resource": {
        "resourceType": "Organization",
        "id": "7ffe74ac-786d-3c6d-bcb9-323352f6149c",
        "extension": [
          {
            "url": "http://synthetichealth.github.io/synthea/utilization-encounters-extension",
            "valueInteger": 4
          },
          {
            "url": "http://synthetichealth.github.io/synthea/utilization-procedures-extension",
            "valueInteger": 0
          },
          {
            "url": "http://synthetichealth.github.io/synthea/utilization-labs-extension",
            "valueInteger": 0
          },
          {
            "url": "http://synthetichealth.github.io/synthea/utilization-prescriptions-extension",
            "valueInteger": 0
          }
        ],
        "identifier": [
          {
            "system": "https://github.com/synthetichealth/synthea",
            "value": "7ffe74ac-786d-3c6d-bcb9-323352f6149c"
          }
        ],
        "active": true,
        "type": [
          {
            "coding": [
              {
                "system": "http://terminology.hl7.org/CodeSystem/organization-type",
                "code": "prov",
                "display": "Healthcare Provider"
              }
            ],
            "text": "Healthcare Provider"
          }
        ],
        "name": "CONCENTRA URGENT CARE - SPRINGFIELD",
        "telecom": [
          {
            "system": "phone",
            "value": "413-746-4006"
          }
        ],
        "address": [
          {
            "line": [
              "140 CARANDO DRIVE"
            ],
            "city": "SPRINGFIELD",
            "state": "MA",
            "postalCode": "1104",
            "country": "US"
          }
        ]
      },
      "request": {
        "method": "POST",
        "url": "Organization"
      }
    }
  ]
}
